CMakeLists.txt
LICENSE.md
MANIFEST.in
README.md
packaging_instructions.txt
pyproject.toml
setup.py
cmake/CudaSupportedArchitectures.cmake
cmake/CxxStdAutodetect.cmake
cmake/DEMEConfig.cmake.in
cmake/FixNinjaColors.cmake
data/clumps/3_clump.csv
data/clumps/6_clump.csv
data/clumps/ContactChain_initial.csv
data/clumps/TeddyBear.csv
data/clumps/ViperWheelSimple.csv
data/clumps/ellipsoid_2_1_1.csv
data/clumps/molecule.csv
data/clumps/spiky_sphere.csv
data/clumps/triangular_flat.csv
data/clumps/triangular_flat_6comp.csv
data/mesh/GPBR_Vessel_Fine.obj
data/mesh/cone.obj
data/mesh/cube.obj
data/mesh/cyl_r1_h2.obj
data/mesh/excavator.obj
data/mesh/funnel.obj
data/mesh/funnel_left.obj
data/mesh/hourglass.obj
data/mesh/hourglass_cap.obj
data/mesh/internal_mixer.obj
data/mesh/plane_20by20.obj
data/mesh/silo.obj
data/mesh/sphere.obj
data/mesh/thin_plate.obj
data/mesh/rover_wheels/curiosity_wheel.obj
data/mesh/rover_wheels/curiosity_wheel_surface.obj
data/mesh/rover_wheels/viper_wheel_right.obj
data/sim_data/example_cnt_pairs.csv
deme.egg-info/PKG-INFO
deme.egg-info/SOURCES.txt
deme.egg-info/dependency_links.txt
deme.egg-info/not-zip-safe
deme.egg-info/requires.txt
deme.egg-info/top_level.txt
src/.format_all
src/DEM/API.h
src/DEM/APIPrivate.cpp
src/DEM/APIPublic.cpp
src/DEM/AuxClasses.cpp
src/DEM/AuxClasses.h
src/DEM/BdrsAndObjs.h
src/DEM/CMakeLists.txt
src/DEM/Defines.h
src/DEM/HostSideHelpers.hpp
src/DEM/MeshUtils.cpp
src/DEM/Models.h
src/DEM/PyDEME.cpp
src/DEM/Structs.h
src/DEM/VariableTypes.h
src/DEM/dT.cpp
src/DEM/dT.h
src/DEM/kT.cpp
src/DEM/kT.h
src/DEM/utils/Samplers.hpp
src/algorithms/CMakeLists.txt
src/algorithms/DEMCubContactDetection.cu
src/algorithms/DEMCubForceCollection.cu
src/algorithms/DEMCubInstantiations.cu
src/algorithms/DEMCubWrappers.cu
src/algorithms/DEMDynamicMisc.cu
src/algorithms/DEMStaticDeviceSubroutines.h
src/algorithms/DEMStaticDeviceUtilities.cuh
src/core/ApiVersion.h.in
src/core/CMakeLists.txt
src/core/DebugInfo.cpp
src/core/utils/CudaAllocator.hpp
src/core/utils/DEMEPaths.cpp
src/core/utils/DEMEPaths.h
src/core/utils/DataMigrationHelper.hpp
src/core/utils/GpuError.h
src/core/utils/GpuManager.cpp
