Metadata-Version: 2.4
Name: deme
Version: 2.2.0
Summary: PyBind Wrapper Library for DEM-Engine
Author: Ruochun Zhang
Author-email: ruochunz@gmail.com
License-File: LICENSE.md
Requires-Dist: numpy
Requires-Dist: pybind11
Provides-Extra: dev
Requires-Dist: pybind11; extra == "dev"
Provides-Extra: test
Requires-Dist: pytest>=6.0; extra == "test"
Dynamic: author
Dynamic: author-email
Dynamic: license-file
Dynamic: provides-extra
Dynamic: requires-dist
Dynamic: summary
